csfloat/__init__.py
csfloat/client.py
csfloat/enums.py
csfloat/errors.py
csfloat/http.py
csfloat/item.py
csfloat/iterators.py
csfloat/listing.py
csfloat/user.py
csfloat_py-0.3.0.dist-info/licenses/LICENSE
csfloat_py-0.3.0.dist-info/METADATA
csfloat_py-0.3.0.dist-info/WHEEL
csfloat_py-0.3.0.dist-info/top_level.txt
csfloat_py-0.3.0.dist-info/RECORD
