Metadata-Version: 2.4
Name: csfloat.py
Version: 0.3.0
Summary: A Python wrapper for the csfloat API
Author: PaxxPatriot
License-Expression: MIT
Project-URL: Repository, https://github.com/PaxxPatriot/csfloat.py.git
Project-URL: Issues, https://github.com/PaxxPatriot/csfloat.py/issues
Keywords: csfloat,Counter-Strike 2
Classifier: Development Status :: 3 - Alpha
Classifier: Environment :: Console
Classifier: Framework :: aiohttp
Classifier: Intended Audience :: Developers
Classifier: Natural Language :: English
Classifier: Operating System :: OS Independent
Classifier: Programming Language :: Python :: 3 :: Only
Classifier: Programming Language :: Python :: 3.10
Classifier: Programming Language :: Python :: 3.11
Classifier: Programming Language :: Python :: 3.12
Classifier: Programming Language :: Python :: 3.13
Classifier: Topic :: Internet
Classifier: Topic :: Software Development :: Libraries
Classifier: Topic :: Software Development :: Libraries :: Python Modules
Classifier: Topic :: Utilities
Classifier: Typing :: Typed
Requires-Python: >=3.10
License-File: LICENSE
Requires-Dist: aiohttp
Dynamic: license-file
